easy_mongo/__init__.py
easy_mongo/mongo.py
easy_mongo/mongo_config.py
easy_mongo/mongo_log.py
easy_mongo-0.0.4.dist-info/METADATA
easy_mongo-0.0.4.dist-info/WHEEL
easy_mongo-0.0.4.dist-info/top_level.txt
easy_mongo-0.0.4.dist-info/RECORD
