Metadata-Version: 2.1
Name: easy-mongo
Version: 0.0.4
Summary: easy to use mongo(kb)
Home-page: https://github.com/ksust/easy_mongo
Author: ksust
Author-email: admin@ksust.com
Maintainer: ksust
Maintainer-email: admin@ksust.com
License: UNKNOWN
Platform: all
Classifier: Programming Language :: Python :: 3
Classifier: Programming Language :: Python :: 3.5
Classifier: Programming Language :: Python :: 3.6
Classifier: Programming Language :: Python :: 3.7
Classifier: Programming Language :: Python :: 3.8
Requires-Dist: pymongo (==3.10.1)
Requires-Dist: PyYAML (==5.3.1)
